git_annex_metadata_gui/__init__.py
git_annex_metadata_gui/auto_size_line_edit.py
git_annex_metadata_gui/field_item_edit.py
git_annex_metadata_gui/file_metadata_model.py
git_annex_metadata_gui/file_preview.py
git_annex_metadata_gui/key_metadata_model.py
git_annex_metadata_gui/main_window.py
git_annex_metadata_gui/main_window_ui.py
git_annex_metadata_gui/metadata_edit.py
git_annex_metadata_gui/metadata_table_view.py
git_annex_metadata_gui/metadata_tree_view.py
git_annex_metadata_gui/utils.py
git_annex_metadata_gui-0.2.0.dist-info/DESCRIPTION.rst
git_annex_metadata_gui-0.2.0.dist-info/METADATA
git_annex_metadata_gui-0.2.0.dist-info/RECORD
git_annex_metadata_gui-0.2.0.dist-info/WHEEL
git_annex_metadata_gui-0.2.0.dist-info/entry_points.txt
git_annex_metadata_gui-0.2.0.dist-info/metadata.json
git_annex_metadata_gui-0.2.0.dist-info/top_level.txt
