Metadata-Version: 2.0
Name: git-annex-metadata-gui
Version: 0.2.0
Summary: Graphical interface for git-annex metadata commands
Home-page: https://github.com/alpernebbi/git-annex-metadata-gui
Author: Alper Nebi Yasak
Author-email: alpernebiyasak@gmail.com
License: GPL3+
Keywords: git-annex metadata
Platform: UNKNOWN
Classifier: Development Status :: 3 - Alpha
Classifier: Environment :: X11 Applications :: Qt
Classifier: Intended Audience :: End Users/Desktop
Classifier: Topic :: Utilities
Classifier: License :: OSI Approved :: GNU General Public License v3 or later (GPLv3+)
Classifier: Programming Language :: Python :: 3
Classifier: Programming Language :: Python :: 3.5
Requires-Dist: PyQt5
Requires-Dist: git-annex-adapter (>=0.2.0)
